jangle/__init__.py
jangle/junk_drawer.py
jangle/lifespan.py
jangle/plumbing.py
jangle/schedule.py
jangle-0.0.1.dist-info/LICENSE
jangle-0.0.1.dist-info/WHEEL
jangle-0.0.1.dist-info/METADATA
jangle-0.0.1.dist-info/RECORD
