Metadata-Version: 2.1
Name: jangle
Version: 0.0.1
Summary: Framework for Discord bots with Django
License: agpl-3
Author: Jamie Bliss
Author-email: jamie@ivyleav.es
Requires-Python: >=3.10,<4.0
Classifier: License :: Other/Proprietary License
Classifier: Programming Language :: Python :: 3
Classifier: Programming Language :: Python :: 3.10
Requires-Dist: Django (>=4.0,<4.1)
Requires-Dist: aiohttp (>=3.8.1,<4.0.0)
Requires-Dist: asgiref (>=3.5.0,<4.0.0)
Requires-Dist: channels (>=3.0,<3.1)
Requires-Dist: httpx (>=0.22.0,<0.23.0)
